AkvoResponseGrouper/__init__.py
AkvoResponseGrouper/db.py
AkvoResponseGrouper/models.py
AkvoResponseGrouper/response_grouper.py
AkvoResponseGrouper/routes.py
AkvoResponseGrouper/utils.py
AkvoResponseGrouper/views.py
AkvoResponseGrouper/cli/__init__.py
AkvoResponseGrouper/cli/checker.py
AkvoResponseGrouper/cli/generate_schema.py
AkvoResponseGrouper/cli/migrate.py
AkvoResponseGrouper/tests/__init__.py
AkvoResponseGrouper/tests/conftest.py
AkvoResponseGrouper/tests/test_lib_01_route.py
AkvoResponseGrouper/tests/test_lib_02_utils.py
AkvoResponseGrouper-1.2.0.dist-info/LICENSE
AkvoResponseGrouper-1.2.0.dist-info/METADATA
AkvoResponseGrouper-1.2.0.dist-info/WHEEL
AkvoResponseGrouper-1.2.0.dist-info/entry_points.txt
AkvoResponseGrouper-1.2.0.dist-info/top_level.txt
AkvoResponseGrouper-1.2.0.dist-info/RECORD
