Metadata-Version: 2.1
Name: AkvoResponseGrouper
Version: 1.2.0
Summary: Fast-API Response catalog for pre-computed query
Home-page: https://github.com/akvo/Akvo-ResponseGrouper
Author: Akvo
Author-email: tech.consultancy@akvo.org
Project-URL: Documentation, https://github.com/akvo/Akvo-ResponseGrouper
Project-URL: Bug Reports, https://github.com/akvo/Akvo-ResponseGrouper/issues
Project-URL: Source Code, https://github.com/akvo/Akvo-ResponseGrouper
Keywords: akvo,data,helper,pypi,package
Classifier: Development Status :: 4 - Beta
Classifier: Intended Audience :: Developers
Classifier: Topic :: Software Development :: Build Tools
Classifier: Topic :: Database :: Database Engines/Servers
Classifier: Programming Language :: Python :: 3
Classifier: Programming Language :: Python :: 3.8
Classifier: Programming Language :: Python :: 3.9
Classifier: Programming Language :: Python :: 3 :: Only
Classifier: Framework :: FastAPI
Classifier: License :: OSI Approved :: GNU Affero General Public License v3
Classifier: Operating System :: OS Independent
Requires-Python: >=3.8.5
License-File: LICENSE
Requires-Dist: fastapi
Requires-Dist: pydantic
Requires-Dist: sqlalchemy
Provides-Extra: dev
Requires-Dist: check-manifest ; extra == 'dev'
Provides-Extra: test
Requires-Dist: httpx ; extra == 'test'
